{
	"schemaVersion": 1,
	"id": "untitled_dimension_mod",
	"version": "${version}",
	"name": "Untitled Dimension Mod",
	"description": "TODO",
	"authors": [
		"Zachary Barbanell"
	],
	"contact": {
		"sources": "https://github.com/zacharybarbanell/untitled-dimension-mod"
	},
	"license": "MIT",
	"icon": "assets/dimmod/icon.png",
	"environment": "*",
	"entrypoints": {
		"main": [
			"com.zacharybarbanell.dimmod.ExampleMod"
		],
		"client": [
			"com.zacharybarbanell.dimmod.ExampleModClient"
		]
	},
	"mixins": [
		"dimmod.mixins.json",
		{
			"config": "dimmod.client.mixins.json",
			"environment": "client"
		}
	],
	"depends": {
		"fabricloader": ">=0.14.21",
		"minecraft": "~1.20.1",
		"java": ">=17",
		"fabric-api": "*"
	},
	"suggests": {
		"another-mod": "*"
	},
	"accessWidener": "dimmod.accesswidener"
}